[{"author":{"login":"coderabbitai"},"headRefName":"coderabbitai/docstrings/f7d37d7","labels":[],"mergeable":"MERGEABLE","number":19,"reviewDecision":"","title":"📝 Add docstrings to `codex/add-test-fixtures-for-playwright-support`","url":"https://github.com/mruderman/subjective-priority-driven-swarm/pull/19"},{"author":{"login":"mruderman"},"headRefName":"codex/automate-export-variants-from-chat-interface","labels":[{"id":"LA_kwDOPTZ1ys8AAAACKgQ2hg","name":"codex","description":"","color":"ededed"}],"mergeable":"MERGEABLE","number":18,"reviewDecision":"","title":"Add secretary export UI automation","url":"https://github.com/mruderman/subjective-priority-driven-swarm/pull/18"},{"author":{"login":"mruderman"},"headRefName":"codex/add-test-fixtures-for-playwright-support","labels":[{"id":"LA_kwDOPTZ1ys8AAAACKgQ2hg","name":"codex","description":"","color":"ededed"}],"mergeable":"MERGEABLE","number":17,"reviewDecision":"","title":"Add Playwright fixtures for deterministic mocked Letta","url":"https://github.com/mruderman/subjective-priority-driven-swarm/pull/17"},{"author":{"login":"mruderman"},"headRefName":"codex/expand-browser-tests-for-session-lifecycle","labels":[{"id":"LA_kwDOPTZ1ys8AAAACKgQ2hg","name":"codex","description":"","color":"ededed"}],"mergeable":"MERGEABLE","number":16,"reviewDecision":"CHANGES_REQUESTED","title":"Add Playwright coverage for session lifecycle flows","url":"https://github.com/mruderman/subjective-priority-driven-swarm/pull/16"},{"author":{"login":"mruderman"},"headRefName":"codex/script-in-chat-commands-and-ui-updates","labels":[{"id":"LA_kwDOPTZ1ys8AAAACKgQ2hg","name":"codex","description":"","color":"ededed"}],"mergeable":"MERGEABLE","number":15,"reviewDecision":"CHANGES_REQUESTED","title":"Add slash command coverage for secretary UI","url":"https://github.com/mruderman/subjective-priority-driven-swarm/pull/15"}]
